{
    "aed1": "22050",
    "aed2": "22000",
    "afn1": "1145",
    "afn2": "1140",
    "amd1": "2030",
    "amd2": "2025",
    "aud1": "50000",
    "aud2": "49900",
    "azadi1": "53700000",
    "azadi12": "53100000",
    "azadi1_2": "30600000",
    "azadi1_22": "30200000",
    "azadi1_4": "18000000",
    "azadi1_42": "17700000",
    "azadi1g": "8500000",
    "azadi1g2": "8300000",
    "azn1": "47350",
    "azn2": "47250",
    "bhd1": "213000",
    "bhd2": "212500",
    "bitcoin": "95884.93",
    "bourse": "1904324.2",
    "cad1": "55800",
    "cad2": "55700",
    "chf1": "89250",
    "chf2": "89150",
    "cny1": "11000",
    "cny2": "11000",
    "created": "December 26, 2024 00:01",
    "day": 6,
    "dkk1": "11200",
    "dkk2": "11100",
    "emami1": "56000000",
    "emami12": "55400000",
    "eur1": "83550",
    "eur2": "83450",
    "gbp1": "100600",
    "gbp2": "100400",
    "gol18": "5156055",
    "hkd1": "10350",
    "hkd2": "10250",
    "hour": "19",
    "inr1": "940",
    "inr2": "935",
    "iqd1": "6145",
    "iqd2": "6135",
    "jpy1": "5095",
    "jpy2": "5085",
    "kwd1": "260700",
    "kwd2": "260300",
    "last_modified": "December 26, 2024 15:42",
    "minute": "12",
    "mithqal": "22335000",
    "month": 10,
    "myr1": "18000",
    "myr2": "17900",
    "nok1": "7060",
    "nok2": "7045",
    "omr1": "208700",
    "omr2": "208400",
    "ounce": "2635.16",
    "qar1": "22150",
    "qar2": "22050",
    "rub1": "805",
    "rub2": "800",
    "sar1": "21400",
    "sar2": "21300",
    "second": "23",
    "sek1": "7255",
    "sek2": "7240",
    "sgd1": "59100",
    "sgd2": "59000",
    "thb1": "2350",
    "thb2": "2345",
    "try1": "2280",
    "try2": "2260",
    "usd1": "80350",
    "usd2": "80250",
    "weekday": "Thursday",
    "year": 1403
}