{
    "aed1": "18700",
    "aed2": "18650",
    "afn1": "995",
    "afn2": "990",
    "amd1": "1750",
    "amd2": "1745",
    "aud1": "44150",
    "aud2": "44050",
    "azadi1": "47300000",
    "azadi12": "46500000",
    "azadi1_2": "25600000",
    "azadi1_22": "25200000",
    "azadi1_4": "15900000",
    "azadi1_42": "15500000",
    "azadi1g": "7400000",
    "azadi1g2": "7000000",
    "azn1": "40100",
    "azn2": "40000",
    "bhd1": "181250",
    "bhd2": "180750",
    "bitcoin": "91344.45",
    "bourse": "1904324.2",
    "cad1": "48750",
    "cad2": "48650",
    "chf1": "76800",
    "chf2": "76700",
    "cny1": "9430",
    "cny2": "9410",
    "created": "November 14, 2024 00:01",
    "day": 24,
    "dkk1": "9635",
    "dkk2": "9535",
    "emami1": "49900000",
    "emami12": "49500000",
    "eur1": "71850",
    "eur2": "71750",
    "gbp1": "86450",
    "gbp2": "86250",
    "gol18": "4293365",
    "hkd1": "8775",
    "hkd2": "8745",
    "hour": "15",
    "inr1": "810",
    "inr2": "805",
    "iqd1": "5170",
    "iqd2": "5160",
    "jpy1": "4375",
    "jpy2": "4365",
    "kwd1": "221950",
    "kwd2": "221550",
    "last_modified": "November 14, 2024 11:52",
    "minute": "22",
    "mithqal": "18598000",
    "month": 8,
    "myr1": "15250",
    "myr2": "15150",
    "nok1": "6115",
    "nok2": "6100",
    "omr1": "177400",
    "omr2": "177100",
    "ounce": "2553.84",
    "qar1": "18600",
    "qar2": "18500",
    "rub1": "685",
    "rub2": "680",
    "sar1": "18200",
    "sar2": "18100",
    "second": "21",
    "sek1": "6185",
    "sek2": "6170",
    "sgd1": "50700",
    "sgd2": "50600",
    "thb1": "1945",
    "thb2": "1940",
    "try1": "1985",
    "try2": "1965",
    "usd1": "68300",
    "usd2": "68200",
    "weekday": "Thursday",
    "year": 1403
}