{
    "aed1": "19760",
    "aed2": "19710",
    "afn1": "1045",
    "afn2": "1040",
    "amd1": "1800",
    "amd2": "1795",
    "aud1": "46350",
    "aud2": "46250",
    "azadi1": "50100000",
    "azadi12": "49600000",
    "azadi1_2": "27250000",
    "azadi1_22": "27000000",
    "azadi1_4": "17050000",
    "azadi1_42": "16900000",
    "azadi1g": "8200000",
    "azadi1g2": "8000000",
    "azn1": "42400",
    "azn2": "42300",
    "bhd1": "191800",
    "bhd2": "191300",
    "bitcoin": "98652.86",
    "bourse": "1904324.2",
    "cad1": "51050",
    "cad2": "50950",
    "chf1": "82200",
    "chf2": "82100",
    "cny1": "9935",
    "cny2": "9915",
    "created": "December 09, 2024 00:01",
    "day": 19,
    "dkk1": "10250",
    "dkk2": "10150",
    "emami1": "52200000",
    "emami12": "51700000",
    "eur1": "76250",
    "eur2": "76150",
    "gbp1": "92150",
    "gbp2": "91950",
    "gol18": "4676116",
    "hkd1": "9295",
    "hkd2": "9265",
    "hour": "12",
    "inr1": "855",
    "inr2": "850",
    "iqd1": "5500",
    "iqd2": "5490",
    "jpy1": "4810",
    "jpy2": "4800",
    "kwd1": "235250",
    "kwd2": "234850",
    "last_modified": "December 09, 2024 09:28",
    "minute": "59",
    "mithqal": "20256000",
    "month": 9,
    "myr1": "16350",
    "myr2": "16250",
    "nok1": "6480",
    "nok2": "6465",
    "omr1": "187800",
    "omr2": "187500",
    "ounce": "2653.66",
    "qar1": "19750",
    "qar2": "19650",
    "rub1": "725",
    "rub2": "720",
    "sar1": "19250",
    "sar2": "19150",
    "second": "04",
    "sek1": "6605",
    "sek2": "6590",
    "sgd1": "53900",
    "sgd2": "53800",
    "thb1": "2130",
    "thb2": "2125",
    "try1": "2075",
    "try2": "2055",
    "usd1": "72300",
    "usd2": "72200",
    "weekday": "Monday",
    "year": 1403
}