{
    "aed1": "18400",
    "aed2": "18350",
    "afn1": "985",
    "afn2": "980",
    "amd1": "1730",
    "amd2": "1725",
    "aud1": "44300",
    "aud2": "44200",
    "azadi1": "47000000",
    "azadi12": "46100000",
    "azadi1_2": "24900000",
    "azadi1_22": "24500000",
    "azadi1_4": "14900000",
    "azadi1_42": "14500000",
    "azadi1g": "7200000",
    "azadi1g2": "6800000",
    "azn1": "39600",
    "azn2": "39500",
    "bhd1": "178550",
    "bhd2": "178050",
    "bitcoin": "82146.31",
    "bourse": "1904324.2",
    "cad1": "48300",
    "cad2": "48200",
    "chf1": "76600",
    "chf2": "76500",
    "cny1": "9350",
    "cny2": "9330",
    "created": "November 11, 2024 00:01",
    "day": 21,
    "dkk1": "9640",
    "dkk2": "9540",
    "emami1": "48600000",
    "emami12": "48000000",
    "eur1": "71900",
    "eur2": "71800",
    "gbp1": "86800",
    "gbp2": "86600",
    "gol18": "4365159",
    "hkd1": "8655",
    "hkd2": "8625",
    "hour": "14",
    "inr1": "795",
    "inr2": "790",
    "iqd1": "5105",
    "iqd2": "5095",
    "jpy1": "4380",
    "jpy2": "4370",
    "kwd1": "219150",
    "kwd2": "218750",
    "last_modified": "November 11, 2024 10:39",
    "minute": "09",
    "mithqal": "18909000",
    "month": 8,
    "myr1": "15250",
    "myr2": "15150",
    "nok1": "6090",
    "nok2": "6075",
    "omr1": "174800",
    "omr2": "174500",
    "ounce": "2669.11",
    "qar1": "18350",
    "qar2": "18250",
    "rub1": "685",
    "rub2": "680",
    "sar1": "17900",
    "sar2": "17800",
    "second": "33",
    "sek1": "6195",
    "sek2": "6180",
    "sgd1": "50550",
    "sgd2": "50450",
    "thb1": "1960",
    "thb2": "1955",
    "try1": "1960",
    "try2": "1940",
    "usd1": "67300",
    "usd2": "67200",
    "weekday": "Monday",
    "year": 1403
}