{
    "aed1": "20140",
    "aed2": "20090",
    "afn1": "1070",
    "afn2": "1065",
    "amd1": "1875",
    "amd2": "1870",
    "aud1": "46850",
    "aud2": "46750",
    "azadi1": "51300000",
    "azadi12": "50500000",
    "azadi1_2": "28000000",
    "azadi1_22": "27600000",
    "azadi1_4": "17500000",
    "azadi1_42": "17200000",
    "azadi1g": "8300000",
    "azadi1g2": "8100000",
    "azn1": "43800",
    "azn2": "43700",
    "bhd1": "195400",
    "bhd2": "194900",
    "bitcoin": "98274.28",
    "bourse": "1904324.2",
    "cad1": "52000",
    "cad2": "51900",
    "chf1": "83350",
    "chf2": "83250",
    "cny1": "10150",
    "cny2": "10150",
    "created": "December 11, 2024 00:01",
    "day": 21,
    "dkk1": "10400",
    "dkk2": "10300",
    "emami1": "53400000",
    "emami12": "53000000",
    "eur1": "77400",
    "eur2": "77300",
    "gbp1": "93950",
    "gbp2": "93750",
    "gol18": "4833787",
    "hkd1": "9480",
    "hkd2": "9450",
    "hour": "14",
    "inr1": "870",
    "inr2": "865",
    "iqd1": "5625",
    "iqd2": "5615",
    "jpy1": "4860",
    "jpy2": "4850",
    "kwd1": "239650",
    "kwd2": "239250",
    "last_modified": "December 11, 2024 10:52",
    "minute": "22",
    "mithqal": "20939000",
    "month": 9,
    "myr1": "16650",
    "myr2": "16550",
    "nok1": "6595",
    "nok2": "6580",
    "omr1": "191450",
    "omr2": "191150",
    "ounce": "2693.93",
    "qar1": "20200",
    "qar2": "20100",
    "rub1": "715",
    "rub2": "710",
    "sar1": "19600",
    "sar2": "19500",
    "second": "54",
    "sek1": "6705",
    "sek2": "6690",
    "sgd1": "54850",
    "sgd2": "54750",
    "thb1": "2175",
    "thb2": "2170",
    "try1": "2115",
    "try2": "2095",
    "usd1": "73700",
    "usd2": "73600",
    "weekday": "Wednesday",
    "year": 1403
}