{
    "aed1": "18720",
    "aed2": "18670",
    "afn1": "1025",
    "afn2": "1020",
    "amd1": "1765",
    "amd2": "1760",
    "aud1": "44750",
    "aud2": "44650",
    "azadi1": "49300000",
    "azadi12": "48500000",
    "azadi1_2": "27800000",
    "azadi1_22": "27300000",
    "azadi1_4": "17800000",
    "azadi1_42": "17300000",
    "azadi1g": "8700000",
    "azadi1g2": "8300000",
    "azn1": "40100",
    "azn2": "40000",
    "bhd1": "181350",
    "bhd2": "180850",
    "bitcoin": "70390.7",
    "bourse": "1904324.2",
    "cad1": "49000",
    "cad2": "48900",
    "chf1": "79050",
    "chf2": "78950",
    "cny1": "9600",
    "cny2": "9580",
    "created": "October 31, 2024 00:01",
    "day": 10,
    "dkk1": "9950",
    "dkk2": "9850",
    "emami1": "53100000",
    "emami12": "52000000",
    "eur1": "74200",
    "eur2": "74100",
    "gbp1": "87900",
    "gbp2": "87700",
    "gol18": "4582621",
    "hkd1": "8795",
    "hkd2": "8765",
    "hour": "20",
    "inr1": "810",
    "inr2": "805",
    "iqd1": "5220",
    "iqd2": "5210",
    "jpy1": "4490",
    "jpy2": "4480",
    "kwd1": "222900",
    "kwd2": "222500",
    "last_modified": "October 31, 2024 16:44",
    "minute": "14",
    "mithqal": "19851000",
    "month": 8,
    "myr1": "15600",
    "myr2": "15500",
    "nok1": "6190",
    "nok2": "6175",
    "omr1": "177550",
    "omr2": "177250",
    "ounce": "2740.25",
    "qar1": "18750",
    "qar2": "18650",
    "rub1": "700",
    "rub2": "695",
    "sar1": "18200",
    "sar2": "18100",
    "second": "37",
    "sek1": "6385",
    "sek2": "6370",
    "sgd1": "51650",
    "sgd2": "51550",
    "thb1": "2020",
    "thb2": "2015",
    "try1": "1995",
    "try2": "1975",
    "usd1": "68350",
    "usd2": "68250",
    "weekday": "Thursday",
    "year": 1403
}