{
    "aed1": "19740",
    "aed2": "19690",
    "afn1": "1060",
    "afn2": "1055",
    "amd1": "1790",
    "amd2": "1785",
    "aud1": "46350",
    "aud2": "46250",
    "azadi1": "50000000",
    "azadi12": "49400000",
    "azadi1_2": "27400000",
    "azadi1_22": "27000000",
    "azadi1_4": "16950000",
    "azadi1_42": "16700000",
    "azadi1g": "8200000",
    "azadi1g2": "7900000",
    "azn1": "42250",
    "azn2": "42150",
    "bhd1": "190950",
    "bhd2": "190450",
    "bitcoin": "101948.09",
    "bourse": "1904324.2",
    "cad1": "51200",
    "cad2": "51100",
    "chf1": "81450",
    "chf2": "81350",
    "cny1": "9910",
    "cny2": "9890",
    "created": "December 05, 2024 00:01",
    "day": 15,
    "dkk1": "10150",
    "dkk2": "10050",
    "emami1": "52300000",
    "emami12": "51800000",
    "eur1": "75800",
    "eur2": "75700",
    "gbp1": "91500",
    "gbp2": "91300",
    "gol18": "4682349",
    "hkd1": "9250",
    "hkd2": "9220",
    "hour": "10",
    "inr1": "850",
    "inr2": "845",
    "iqd1": "5500",
    "iqd2": "5490",
    "jpy1": "4795",
    "jpy2": "4785",
    "kwd1": "234200",
    "kwd2": "233800",
    "last_modified": "December 05, 2024 06:52",
    "minute": "22",
    "mithqal": "20283000",
    "month": 9,
    "myr1": "16250",
    "myr2": "16150",
    "nok1": "6520",
    "nok2": "6505",
    "omr1": "187000",
    "omr2": "186700",
    "ounce": "2648.35",
    "qar1": "19750",
    "qar2": "19650",
    "rub1": "685",
    "rub2": "680",
    "sar1": "19150",
    "sar2": "19050",
    "second": "47",
    "sek1": "6595",
    "sek2": "6580",
    "sgd1": "53650",
    "sgd2": "53550",
    "thb1": "2105",
    "thb2": "2100",
    "try1": "2070",
    "try2": "2050",
    "usd1": "72000",
    "usd2": "71900",
    "weekday": "Thursday",
    "year": 1403
}