{
    "aed1": "19000",
    "aed2": "18950",
    "afn1": "1015",
    "afn2": "1010",
    "amd1": "1785",
    "amd2": "1780",
    "aud1": "45250",
    "aud2": "45150",
    "azadi1": "49500000",
    "azadi12": "49000000",
    "azadi1_2": "26600000",
    "azadi1_22": "26300000",
    "azadi1_4": "16600000",
    "azadi1_42": "16200000",
    "azadi1g": "7800000",
    "azadi1g2": "7500000",
    "azn1": "40850",
    "azn2": "40750",
    "bhd1": "184400",
    "bhd2": "183900",
    "bitcoin": "97155.22",
    "bourse": "1904324.2",
    "cad1": "49750",
    "cad2": "49650",
    "chf1": "78700",
    "chf2": "78600",
    "cny1": "9595",
    "cny2": "9575",
    "created": "November 21, 2024 00:01",
    "day": 1,
    "dkk1": "9825",
    "dkk2": "9725",
    "emami1": "52400000",
    "emami12": "52000000",
    "eur1": "73300",
    "eur2": "73200",
    "gbp1": "87900",
    "gbp2": "87700",
    "gol18": "4535527",
    "hkd1": "8930",
    "hkd2": "8900",
    "hour": "11",
    "inr1": "825",
    "inr2": "820",
    "iqd1": "5300",
    "iqd2": "5290",
    "jpy1": "4480",
    "jpy2": "4470",
    "kwd1": "225950",
    "kwd2": "225550",
    "last_modified": "November 21, 2024 07:31",
    "minute": "01",
    "mithqal": "19647000",
    "month": 9,
    "myr1": "15550",
    "myr2": "15450",
    "nok1": "6290",
    "nok2": "6275",
    "omr1": "180550",
    "omr2": "180250",
    "ounce": "2662.29",
    "qar1": "19050",
    "qar2": "18950",
    "rub1": "690",
    "rub2": "685",
    "sar1": "18500",
    "sar2": "18400",
    "second": "27",
    "sek1": "6310",
    "sek2": "6295",
    "sgd1": "51750",
    "sgd2": "51650",
    "thb1": "2000",
    "thb2": "1995",
    "try1": "2015",
    "try2": "1995",
    "usd1": "69500",
    "usd2": "69400",
    "weekday": "Thursday",
    "year": 1403
}