{
    "aed1": "19180",
    "aed2": "19130",
    "afn1": "1015",
    "afn2": "1010",
    "amd1": "1780",
    "amd2": "1775",
    "aud1": "45050",
    "aud2": "44950",
    "azadi1": "49200000",
    "azadi12": "48700000",
    "azadi1_2": "26600000",
    "azadi1_22": "26200000",
    "azadi1_4": "16600000",
    "azadi1_42": "16200000",
    "azadi1g": "7800000",
    "azadi1g2": "7500000",
    "azn1": "40850",
    "azn2": "40750",
    "bhd1": "184650",
    "bhd2": "184150",
    "bitcoin": "93033.15",
    "bourse": "1904324.2",
    "cad1": "49450",
    "cad2": "49350",
    "chf1": "78550",
    "chf2": "78450",
    "cny1": "9595",
    "cny2": "9575",
    "created": "November 27, 2024 00:01",
    "day": 7,
    "dkk1": "9775",
    "dkk2": "9675",
    "emami1": "51400000",
    "emami12": "50700000",
    "eur1": "72900",
    "eur2": "72800",
    "gbp1": "87450",
    "gbp2": "87250",
    "gol18": "4498591",
    "hkd1": "8945",
    "hkd2": "8915",
    "hour": "10",
    "inr1": "825",
    "inr2": "820",
    "iqd1": "5300",
    "iqd2": "5290",
    "jpy1": "4565",
    "jpy2": "4555",
    "kwd1": "226200",
    "kwd2": "225800",
    "last_modified": "November 27, 2024 06:56",
    "minute": "26",
    "mithqal": "19487000",
    "month": 9,
    "myr1": "15650",
    "myr2": "15550",
    "nok1": "6230",
    "nok2": "6215",
    "omr1": "180800",
    "omr2": "180500",
    "ounce": "2645.03",
    "qar1": "19050",
    "qar2": "18950",
    "rub1": "660",
    "rub2": "655",
    "sar1": "18500",
    "sar2": "18400",
    "second": "55",
    "sek1": "6330",
    "sek2": "6315",
    "sgd1": "51650",
    "sgd2": "51550",
    "thb1": "2005",
    "thb2": "2000",
    "try1": "2010",
    "try2": "1990",
    "usd1": "69600",
    "usd2": "69500",
    "weekday": "Wednesday",
    "year": 1403
}