{
    "aed1": "18720",
    "aed2": "18670",
    "afn1": "1025",
    "afn2": "1020",
    "amd1": "1770",
    "amd2": "1765",
    "aud1": "45150",
    "aud2": "45050",
    "azadi1": "49300000",
    "azadi12": "48500000",
    "azadi1_2": "27800000",
    "azadi1_22": "27300000",
    "azadi1_4": "17800000",
    "azadi1_42": "17300000",
    "azadi1g": "8700000",
    "azadi1g2": "8300000",
    "azn1": "40300",
    "azn2": "40200",
    "bhd1": "182000",
    "bhd2": "181500",
    "bitcoin": "71167.17",
    "bourse": "1904324.2",
    "cad1": "49300",
    "cad2": "49200",
    "chf1": "79050",
    "chf2": "78950",
    "cny1": "9635",
    "cny2": "9615",
    "created": "November 01, 2024 00:01",
    "day": 11,
    "dkk1": "10000",
    "dkk2": "9900",
    "emami1": "53100000",
    "emami12": "52000000",
    "eur1": "74550",
    "eur2": "74450",
    "gbp1": "89000",
    "gbp2": "88800",
    "gol18": "4607091",
    "hkd1": "8820",
    "hkd2": "8790",
    "hour": "18",
    "inr1": "815",
    "inr2": "810",
    "iqd1": "5235",
    "iqd2": "5225",
    "jpy1": "4500",
    "jpy2": "4490",
    "kwd1": "223800",
    "kwd2": "223400",
    "last_modified": "November 01, 2024 15:00",
    "minute": "30",
    "mithqal": "19957000",
    "month": 8,
    "myr1": "15650",
    "myr2": "15550",
    "nok1": "6235",
    "nok2": "6220",
    "omr1": "178200",
    "omr2": "177900",
    "ounce": "2745.3",
    "qar1": "18800",
    "qar2": "18700",
    "rub1": "700",
    "rub2": "695",
    "sar1": "18250",
    "sar2": "18150",
    "second": "06",
    "sek1": "6420",
    "sek2": "6405",
    "sgd1": "51850",
    "sgd2": "51750",
    "thb1": "2025",
    "thb2": "2020",
    "try1": "2000",
    "try2": "1980",
    "usd1": "68600",
    "usd2": "68500",
    "weekday": "Friday",
    "year": 1403
}