{
    "aed1": "22140",
    "aed2": "22090",
    "afn1": "1140",
    "afn2": "1135",
    "amd1": "2010",
    "amd2": "2005",
    "aud1": "50250",
    "aud2": "50150",
    "azadi1": "54000000",
    "azadi12": "53100000",
    "azadi1_2": "31100000",
    "azadi1_22": "30500000",
    "azadi1_4": "18000000",
    "azadi1_42": "17500000",
    "azadi1g": "8700000",
    "azadi1g2": "8400000",
    "azn1": "47250",
    "azn2": "47150",
    "bhd1": "213050",
    "bhd2": "212550",
    "bitcoin": "93327.02",
    "bourse": "1904324.2",
    "cad1": "55900",
    "cad2": "55800",
    "chf1": "89250",
    "chf2": "89150",
    "cny1": "11050",
    "cny2": "11050",
    "created": "December 30, 2024 00:01",
    "day": 10,
    "dkk1": "11250",
    "dkk2": "11150",
    "emami1": "56300000",
    "emami12": "55300000",
    "eur1": "83950",
    "eur2": "83850",
    "gbp1": "101300",
    "gbp2": "101100",
    "gol18": "5149360",
    "hkd1": "10350",
    "hkd2": "10250",
    "hour": "11",
    "inr1": "940",
    "inr2": "935",
    "iqd1": "6135",
    "iqd2": "6125",
    "jpy1": "5100",
    "jpy2": "5090",
    "kwd1": "261250",
    "kwd2": "260850",
    "last_modified": "December 30, 2024 07:30",
    "minute": "00",
    "mithqal": "22306000",
    "month": 10,
    "myr1": "18000",
    "myr2": "17900",
    "nok1": "7090",
    "nok2": "7075",
    "omr1": "209100",
    "omr2": "208800",
    "ounce": "2619.17",
    "qar1": "22050",
    "qar2": "21950",
    "rub1": "760",
    "rub2": "755",
    "sar1": "21450",
    "sar2": "21350",
    "second": "12",
    "sek1": "7320",
    "sek2": "7305",
    "sgd1": "59300",
    "sgd2": "59200",
    "thb1": "2370",
    "thb2": "2365",
    "try1": "2280",
    "try2": "2260",
    "usd1": "80500",
    "usd2": "80400",
    "weekday": "Monday",
    "year": 1403
}