{
    "aed1": "19520",
    "aed2": "19470",
    "afn1": "1040",
    "afn2": "1035",
    "amd1": "1785",
    "amd2": "1780",
    "aud1": "46000",
    "aud2": "45900",
    "azadi1": "49400000",
    "azadi12": "48800000",
    "azadi1_2": "27000000",
    "azadi1_22": "26500000",
    "azadi1_4": "16800000",
    "azadi1_42": "16400000",
    "azadi1g": "7900000",
    "azadi1g2": "7600000",
    "azn1": "41400",
    "azn2": "41300",
    "bhd1": "187500",
    "bhd2": "187000",
    "bitcoin": "96818.44",
    "bourse": "1904324.2",
    "cad1": "50350",
    "cad2": "50250",
    "chf1": "80100",
    "chf2": "80000",
    "cny1": "9740",
    "cny2": "9720",
    "created": "December 01, 2024 00:01",
    "day": 11,
    "dkk1": "10000",
    "dkk2": "9900",
    "emami1": "51500000",
    "emami12": "50800000",
    "eur1": "74650",
    "eur2": "74550",
    "gbp1": "89850",
    "gbp2": "89650",
    "gol18": "4579158",
    "hkd1": "9065",
    "hkd2": "9035",
    "hour": "11",
    "inr1": "835",
    "inr2": "830",
    "iqd1": "5395",
    "iqd2": "5385",
    "jpy1": "4710",
    "jpy2": "4700",
    "kwd1": "229500",
    "kwd2": "229100",
    "last_modified": "December 01, 2024 08:25",
    "minute": "55",
    "mithqal": "19836000",
    "month": 9,
    "myr1": "15850",
    "myr2": "15750",
    "nok1": "6385",
    "nok2": "6370",
    "omr1": "183300",
    "omr2": "183000",
    "ounce": "2649.87",
    "qar1": "19400",
    "qar2": "19300",
    "rub1": "660",
    "rub2": "655",
    "sar1": "18800",
    "sar2": "18700",
    "second": "44",
    "sek1": "6470",
    "sek2": "6455",
    "sgd1": "52650",
    "sgd2": "52550",
    "thb1": "2055",
    "thb2": "2050",
    "try1": "2035",
    "try2": "2015",
    "usd1": "70550",
    "usd2": "70450",
    "weekday": "Sunday",
    "year": 1403
}