{
    "aed1": "22300",
    "aed2": "22250",
    "afn1": "1165",
    "afn2": "1160",
    "amd1": "2060",
    "amd2": "2055",
    "aud1": "50800",
    "aud2": "50700",
    "azadi1": "54600000",
    "azadi12": "54000000",
    "azadi1_2": "31300000",
    "azadi1_22": "30800000",
    "azadi1_4": "18200000",
    "azadi1_42": "17800000",
    "azadi1g": "8800000",
    "azadi1g2": "8500000",
    "azn1": "48100",
    "azn2": "48000",
    "bhd1": "216750",
    "bhd2": "216250",
    "bitcoin": "91764.05",
    "bourse": "1904324.2",
    "cad1": "56700",
    "cad2": "56600",
    "chf1": "90300",
    "chf2": "90200",
    "cny1": "11200",
    "cny2": "11200",
    "created": "December 30, 2024 00:01",
    "day": 10,
    "dkk1": "11400",
    "dkk2": "11300",
    "emami1": "56800000",
    "emami12": "56400000",
    "eur1": "84950",
    "eur2": "84850",
    "gbp1": "102550",
    "gbp2": "102350",
    "gol18": "5233851",
    "hkd1": "10550",
    "hkd2": "10450",
    "hour": "19",
    "inr1": "955",
    "inr2": "950",
    "iqd1": "6245",
    "iqd2": "6235",
    "jpy1": "5210",
    "jpy2": "5200",
    "kwd1": "265350",
    "kwd2": "264950",
    "last_modified": "December 30, 2024 16:14",
    "minute": "44",
    "mithqal": "22672000",
    "month": 10,
    "myr1": "18300",
    "myr2": "18200",
    "nok1": "7185",
    "nok2": "7170",
    "omr1": "212300",
    "omr2": "212000",
    "ounce": "2602.45",
    "qar1": "22450",
    "qar2": "22350",
    "rub1": "755",
    "rub2": "750",
    "sar1": "21750",
    "sar2": "21650",
    "second": "37",
    "sek1": "7400",
    "sek2": "7385",
    "sgd1": "60200",
    "sgd2": "60100",
    "thb1": "2390",
    "thb2": "2385",
    "try1": "2315",
    "try2": "2295",
    "usd1": "81750",
    "usd2": "81650",
    "weekday": "Monday",
    "year": 1403
}