{
    "aed1": "19860",
    "aed2": "19810",
    "afn1": "1050",
    "afn2": "1045",
    "amd1": "1810",
    "amd2": "1805",
    "aud1": "46400",
    "aud2": "46300",
    "azadi1": "50500000",
    "azadi12": "50000000",
    "azadi1_2": "27400000",
    "azadi1_22": "27100000",
    "azadi1_4": "17300000",
    "azadi1_42": "17000000",
    "azadi1g": "8250000",
    "azadi1g2": "8000000",
    "azn1": "42250",
    "azn2": "42150",
    "bhd1": "192550",
    "bhd2": "192050",
    "bitcoin": "97068.63",
    "bourse": "1904324.2",
    "cad1": "51200",
    "cad2": "51100",
    "chf1": "82700",
    "chf2": "82600",
    "cny1": "10000",
    "cny2": "10000",
    "created": "December 10, 2024 00:01",
    "day": 20,
    "dkk1": "10300",
    "dkk2": "10200",
    "emami1": "52700000",
    "emami12": "52100000",
    "eur1": "76650",
    "eur2": "76550",
    "gbp1": "92550",
    "gbp2": "92350",
    "gol18": "4718823",
    "hkd1": "9335",
    "hkd2": "9305",
    "hour": "12",
    "inr1": "855",
    "inr2": "850",
    "iqd1": "5535",
    "iqd2": "5525",
    "jpy1": "4795",
    "jpy2": "4785",
    "kwd1": "236150",
    "kwd2": "235750",
    "last_modified": "December 10, 2024 08:16",
    "minute": "04",
    "mithqal": "20441000",
    "month": 9,
    "myr1": "16400",
    "myr2": "16300",
    "nok1": "6530",
    "nok2": "6515",
    "omr1": "188600",
    "omr2": "188300",
    "ounce": "2663.68",
    "qar1": "19900",
    "qar2": "19800",
    "rub1": "720",
    "rub2": "715",
    "sar1": "19300",
    "sar2": "19200",
    "second": "12",
    "sek1": "6640",
    "sek2": "6625",
    "sgd1": "54200",
    "sgd2": "54100",
    "thb1": "2155",
    "thb2": "2150",
    "try1": "2085",
    "try2": "2065",
    "usd1": "72600",
    "usd2": "72500",
    "weekday": "Tuesday",
    "year": 1403
}